[
  {"id":"nike","name":"Nike Store","category":"Fashion","tags":["shoes","sneakers","sportswear","athletic"],"floor":2,"logo_bg":"bg-gray-800","logo_text":"N","logo_color":"text-white","hours":"10:00 AM - 9:00 PM","phone":"+1 (555) 123-4567"},
  {"id":"uniqlo","name":"Uniqlo","category":"Fashion","tags":["clothing","casual","basics","japanese"],"floor":1,"logo_bg":"bg-red-600","logo_text":"U","logo_color":"text-white","hours":"10:00 AM - 9:00 PM","phone":"+1 (555) 234-5678"},
  {"id":"zara","name":"Zara","category":"Fashion","tags":["clothing","trendy","european","women"],"floor":1,"logo_bg":"bg-black","logo_text":"Z","logo_color":"text-white","hours":"10:00 AM - 9:00 PM","phone":"+1 (555) 345-6789"},
  {"id":"hm","name":"H&M","category":"Fashion","tags":["clothing","affordable","basics","sustainable"],"floor":2,"logo_bg":"bg-red-500","logo_text":"H","logo_color":"text-white","hours":"10:00 AM - 9:00 PM","phone":"+1 (555) 456-7890"},
  {"id":"apple","name":"Apple Store","category":"Electronics","tags":["phones","laptops","tablets","tech","iphone","macbook"],"floor":2,"logo_bg":"bg-gray-100","logo_text":"A","logo_color":"text-gray-800","hours":"10:00 AM - 9:00 PM","phone":"+1 (555) 567-8901"},
  {"id":"samsung","name":"Samsung Experience","category":"Electronics","tags":["phones","galaxy","tech","android","tv"],"floor":2,"logo_bg":"bg-blue-600","logo_text":"S","logo_color":"text-white","hours":"10:00 AM - 9:00 PM","phone":"+1 (555) 678-9012"},
  {"id":"bestbuy","name":"Best Buy","category":"Electronics","tags":["gadgets","computers","gaming","appliances"],"floor":1,"logo_bg":"bg-yellow-400","logo_text":"B","logo_color":"text-blue-800","hours":"10:00 AM - 9:00 PM","phone":"+1 (555) 789-0123"},
  {"id":"sephora","name":"Sephora","category":"Health & Beauty","tags":["makeup","cosmetics","skincare","fragrance"],"floor":1,"logo_bg":"bg-black","logo_text":"S","logo_color":"text-white","hours":"10:00 AM - 9:00 PM","phone":"+1 (555) 890-1234"},
  {"id":"watsons","name":"Watsons","category":"Health & Beauty","tags":["pharmacy","health","wellness","personal care"],"floor":1,"logo_bg":"bg-teal-500","logo_text":"W","logo_color":"text-white","hours":"10:00 AM - 10:00 PM","phone":"+1 (555) 901-2345"},
  {"id":"bath-body","name":"Bath & Body Works","category":"Health & Beauty","tags":["candles","body care","fragrance","lotion"],"floor":2,"logo_bg":"bg-blue-800","logo_text":"B","logo_color":"text-white","hours":"10:00 AM - 9:00 PM","phone":"+1 (555) 012-3456"},
  {"id":"sakura","name":"Sakura Sushi","category":"Food & Dining","tags":["japanese","sushi","ramen","asian"],"floor":1,"logo_bg":"bg-rose-500","logo_text":"S","logo_color":"text-white","hours":"11:00 AM - 10:00 PM","phone":"+1 (555) 111-2222"},
  {"id":"burger-hub","name":"Burger Hub","category":"Food & Dining","tags":["burgers","fries","fast food","american"],"floor":1,"logo_bg":"bg-amber-500","logo_text":"B","logo_color":"text-white","hours":"10:00 AM - 10:00 PM","phone":"+1 (555) 222-3333"},
  {"id":"cafe-mocha","name":"Cafe Mocha","category":"Food & Dining","tags":["coffee","tea","pastries","breakfast","cafe"],"floor":2,"logo_bg":"bg-amber-800","logo_text":"C","logo_color":"text-white","hours":"7:00 AM - 9:00 PM","phone":"+1 (555) 333-4444"},
  {"id":"pizza-palace","name":"Pizza Palace","category":"Food & Dining","tags":["pizza","italian","pasta","delivery"],"floor":1,"logo_bg":"bg-red-600","logo_text":"P","logo_color":"text-white","hours":"11:00 AM - 10:00 PM","phone":"+1 (555) 444-5555"},
  {"id":"seoul-kitchen","name":"Seoul Kitchen","category":"Food & Dining","tags":["korean","bbq","bibimbap","asian"],"floor":1,"logo_bg":"bg-red-700","logo_text":"S","logo_color":"text-white","hours":"11:00 AM - 10:00 PM","phone":"+1 (555) 555-6666"},
  {"id":"sweet-tooth","name":"Sweet Tooth","category":"Food & Dining","tags":["dessert","ice cream","cake","sweets"],"floor":2,"logo_bg":"bg-pink-400","logo_text":"S","logo_color":"text-white","hours":"10:00 AM - 9:00 PM","phone":"+1 (555) 666-7777"},
  {"id":"cinema","name":"Greenfield Cinema","category":"Entertainment","tags":["movies","film","imax","3d"],"floor":3,"logo_bg":"bg-purple-700","logo_text":"G","logo_color":"text-white","hours":"10:00 AM - 12:00 AM","phone":"+1 (555) 777-8888"},
  {"id":"arcade","name":"Fun Zone Arcade","category":"Entertainment","tags":["games","arcade","bowling","fun"],"floor":3,"logo_bg":"bg-indigo-500","logo_text":"F","logo_color":"text-white","hours":"10:00 AM - 10:00 PM","phone":"+1 (555) 888-9999"},
  {"id":"ikea","name":"IKEA Home","category":"Home & Living","tags":["furniture","home decor","kitchen","bedroom"],"floor":3,"logo_bg":"bg-blue-600","logo_text":"I","logo_color":"text-yellow-300","hours":"10:00 AM - 9:00 PM","phone":"+1 (555) 999-0000"},
  {"id":"muji","name":"MUJI","category":"Home & Living","tags":["minimalist","stationery","home goods","japanese"],"floor":2,"logo_bg":"bg-red-700","logo_text":"M","logo_color":"text-white","hours":"10:00 AM - 9:00 PM","phone":"+1 (555) 000-1111"},
  {"id":"daiso","name":"Daiso","category":"Home & Living","tags":["variety","dollar store","household","japanese"],"floor":1,"logo_bg":"bg-pink-500","logo_text":"D","logo_color":"text-white","hours":"10:00 AM - 9:00 PM","phone":"+1 (555) 121-3131"}
]